fastapi_injectable/__init__.py
fastapi_injectable/async_exit_stack.py
fastapi_injectable/cache.py
fastapi_injectable/concurrency.py
fastapi_injectable/decorator.py
fastapi_injectable/exception.py
fastapi_injectable/logging.py
fastapi_injectable/main.py
fastapi_injectable/mypy.py
fastapi_injectable/py.typed
fastapi_injectable/util.py
fastapi_injectable-1.4.6.dist-info/METADATA
fastapi_injectable-1.4.6.dist-info/WHEEL
fastapi_injectable-1.4.6.dist-info/licenses/LICENSE
fastapi_injectable-1.4.6.dist-info/RECORD
