Metadata-Version: 2.4
Name: fastapi-injectable
Version: 1.4.6
Summary: Allow you to painlessly use dependency injection mechanism (`Depends`) of FastAPI outside the FastAPI routes
Project-URL: Homepage, https://github.com/JasperSui/fastapi-injectable
Project-URL: Repository, https://github.com/JasperSui/fastapi-injectable
Project-URL: Documentation, https://fastapi-injectable.readthedocs.io
Project-URL: Changelog, https://github.com/JasperSui/fastapi-injectable/releases
Author-email: Jasper Sui <suiyang03@gmail.com>
License-Expression: MIT
License-File: LICENSE
Classifier: Development Status :: 5 - Production/Stable
Classifier: Framework :: FastAPI
Classifier: License :: OSI Approved :: MIT License
Classifier: Programming Language :: Python :: 3.10
Classifier: Programming Language :: Python :: 3.11
Classifier: Programming Language :: Python :: 3.12
Classifier: Programming Language :: Python :: 3.13
Classifier: Programming Language :: Python :: 3.14
Classifier: Programming Language :: Python :: Free Threading :: 3 - Stable
Requires-Python: >=3.10
Requires-Dist: fastapi<1.0.0,>=0.112.4
